roadintel/__init__.py
roadintel/charts.py
roadviz-1.0.0.dist-info/METADATA
roadviz-1.0.0.dist-info/WHEEL
roadviz-1.0.0.dist-info/top_level.txt
roadviz-1.0.0.dist-info/RECORD
