Metadata-Version: 2.4
Name: roadviz
Version: 1.0.0
Summary: A Plotly-based visualization library for road accident data analysis.
Author: Anubhav Shukla
Author-email: anubhavshukla870@gmail.com
Classifier: Programming Language :: Python :: 3
Classifier: License :: OSI Approved :: MIT License
Classifier: Operating System :: OS Independent
Requires-Python: >=3.7
Requires-Dist: pandas
Requires-Dist: plotly
Dynamic: author
Dynamic: author-email
Dynamic: classifier
Dynamic: description
Dynamic: description-content-type
Dynamic: requires-dist
Dynamic: requires-python
Dynamic: summary
